bin/sensemaking-cli.py
deepsensemaking/__init__.py
deepsensemaking/testing/test.py
sensemaking-0.1.2020.5.16.3.data/scripts/sensemaking-cli
sensemaking-0.1.2020.5.16.3.dist-info/LICENSE.txt
sensemaking-0.1.2020.5.16.3.dist-info/METADATA
sensemaking-0.1.2020.5.16.3.dist-info/WHEEL
sensemaking-0.1.2020.5.16.3.dist-info/top_level.txt
sensemaking-0.1.2020.5.16.3.dist-info/RECORD
