Metadata-Version: 2.1
Name: sensemaking
Version: 0.1.2020.5.16.3
Summary: sensemaking (sm)
Home-page: https://github.com/deepsensemaking/sensemaking
Author: DeepSenseMaking Developes
Author-email: deepsensemaking@gmail.com
License: Apache License 2.0
Download-URL: https://github.com/deepsensemaking/sensemaking/releases/download/v0.1.2020.05.16.1/sensemaking-0.1.2020.5.16.1-py3-none-any.whl
Keywords: sensemaking,nlp,ml,ai
Platform: UNKNOWN
Classifier: Development Status :: 2 - Pre-Alpha
Classifier: Operating System :: OS Independent
Classifier: Environment :: Console
Classifier: Intended Audience :: Science/Research
Classifier: Natural Language :: English
Classifier: Programming Language :: Python :: 3 :: Only
Classifier: License :: OSI Approved :: Apache Software License
Requires-Python: >=3.6
Requires-Dist: argparse (>=1.1)
Requires-Dist: pandas (>=1.0.1)
Requires-Dist: numpy (>=1.18.1)
Requires-Dist: scipy (>=1.4.1)
